seval/__init__.py
seval/arithmetic.py
seval/evalable.py
seval/literal.py
seval/math_exp.py
seval/seval.py
seval-1.1.0.dist-info/METADATA
seval-1.1.0.dist-info/RECORD
seval-1.1.0.dist-info/WHEEL
seval-1.1.0.dist-info/top_level.txt
